fast_dynamic_batcher/__init__.py
fast_dynamic_batcher/dyn_batcher.py
fast_dynamic_batcher/dyn_prog_loop.py
fast_dynamic_batcher/errors.py
fast_dynamic_batcher/inference_template.py
fast_dynamic_batcher/models.py
fast_dynamic_batcher-1.1.0.dist-info/licenses/LICENSE
fast_dynamic_batcher-1.1.0.dist-info/METADATA
fast_dynamic_batcher-1.1.0.dist-info/WHEEL
fast_dynamic_batcher-1.1.0.dist-info/top_level.txt
fast_dynamic_batcher-1.1.0.dist-info/RECORD
