Metadata-Version: 2.4
Name: fast_dynamic_batcher
Version: 1.1.0
Summary: FastDynamicBatcher is a library for batching inputs across requests to accelerate machine learning workloads.
Author: Jeffrey Wigger
License-Expression: MIT
Project-URL: repository, https://github.com/JeffWigger/FastDynamicBatcher
Project-URL: homepage, https://github.com/JeffWigger/FastDynamicBatcher
Keywords: machine-learning,batching
Requires-Python: >=3.10
License-File: LICENSE
Dynamic: license-file
